murf_mcp/__init__.py
murf_mcp/claude_setup.py
murf_mcp/model.py
murf_mcp/server.py
murf_mcp/utils.py
murf_mcp-0.1.13.dist-info/licenses/LICENSE
murf_mcp-0.1.13.dist-info/METADATA
murf_mcp-0.1.13.dist-info/WHEEL
murf_mcp-0.1.13.dist-info/entry_points.txt
murf_mcp-0.1.13.dist-info/top_level.txt
murf_mcp-0.1.13.dist-info/RECORD
