Metadata-Version: 2.4
Name: murf-mcp
Version: 0.1.13
Summary: An MCP server for interacting with Murf APIs
Requires-Python: >=3.11
License-File: LICENSE
Requires-Dist: httpx>=0.28.1
Requires-Dist: mcp[cli]>=1.6.0
Requires-Dist: murf>=1.0.2
Requires-Dist: pydub>=0.25.1
Requires-Dist: rapidfuzz>=3.13.0
Dynamic: license-file
